qsplit_mlft/__init__.py
qsplit_mlft/circuit_ansatz.py
qsplit_mlft/collect_data.py
qsplit_mlft/compute_fidelities.py
qsplit_mlft/cutting_methods.py
QSPLIT_MLFT-0.0.1.dist-info/LICENSE.md
QSPLIT_MLFT-0.0.1.dist-info/METADATA
QSPLIT_MLFT-0.0.1.dist-info/WHEEL
QSPLIT_MLFT-0.0.1.dist-info/top_level.txt
QSPLIT_MLFT-0.0.1.dist-info/RECORD
