Metadata-Version: 2.1
Name: QSPLIT-MLFT
Version: 0.0.1
Summary: Divide and Compute with Maximum Likelihood Tomography
Home-page: https://github.com/Quantum-Software-Tools/QSPLIT-MLFT
Author: Michael Perlin
Author-email: mika.perlin@gmail.com
License: 3-Clause BSD
Requires-Python: >=3.8.0
License-File: LICENSE.md
Requires-Dist: autoray (>=0.5.0)
Requires-Dist: cirq (>=1.0.0)
Requires-Dist: numpy (>=1.22.0)
Requires-Dist: opt-einsum (>=3.0.1)
Requires-Dist: quimb (>=1.4.0)
